midterm/encoder_decoder/decoder3to8.v
module decoder3to8(
    input wire [2:0] in,
    input wire en,
    output reg [7:0] out
);

    always@ * begin
        if (en) begin
            case(in)
            3'b000: out = 8'b00000001;
            3'b001: out = 8'b00000010;
            3'b010: out = 8'b00000100;
            3'b011: out = 8'b00001000;
            3'b100: out = 8'b00010000;
            3'b101: out = 8'b00100000;
            3'b110: out = 8'b01000000;
            3'b111: out = 8'b10000000;
            endcase
        end else begin
            out = 8'bzzzzzzzz;
        end
    end
endmodule

midterm/encoder_decoder/tb_decoder3to8.v
`timescale  1ns / 10ps

module tb_decoder3to8;
// signal declaration
reg [2:0] in;
reg en;
wire [7:0] out;

decoder3to8 uut(
    .in(in), .en(en), .out(out));

    initial begin
    $dumpfile("decoder3to8.vcd");
    $dumpvars(0, tb_decoder3to8);

    $display("Time\tin\ten\tout");
    $monitor("\t%b\t%b\t%b", in, en, out);

    in = 3'b001; en = 0; #10;
    in = 8'b100; en = 0; #10;
    in = 8'b100; en = 1; #10;
    in = 8'b000; #10;
    in = 8'b001; #10;
    in = 8'b010; #10;
    in = 8'b110; #10;
    in = 8'b111; #10;

    $finish;
    end
endmodule

midterm/encoder_decoder/decoder3to8.vcd
$date
	Fri May 02 12:52:27 2025
$end
$version
	Icarus Verilog
$end
$timescale
	10ps
$end
$scope module tb_decoder3to8 $end
$var wire 8 ! out [7:0] $end
$var reg 1 " en $end
$var reg 3 # in [2:0] $end
$scope module uut $end
$var wire 1 " en $end
$var wire 3 $ in [2:0] $end
$var reg 8 % out [7:0] $end
$upscope $end
$upscope $end
$enddefinitions $end
$comment Show the parameter values. $end
$dumpall
$end
#0
$dumpvars
bz %
b1 $
b1 #
0"
bz !
$end
#1000
b100 #
b100 $
#2000
b10000 !
b10000 %
1"
#3000
b1 !
b1 %
b0 #
b0 $
#4000
b10 !
b10 %
b1 #
b1 $
#5000
b100 !
b100 %
b10 #
b10 $
#6000
b1000000 !
b1000000 %
b110 #
b110 $
#7000
b10000000 !
b10000000 %
b111 #
b111 $
