midterm/encoder_decoder/decoder2to4.v
module decoder2to4(
    input wire [1:0] in,
    input wire en,
    output reg [3:0] out
);

    always@ * begin
    if (en) begin
        case(in)
        2'b00: out = 4'b0001;
        2'b01: out = 4'b0010;
        2'b10: out = 4'b0100;
        2'b11: out = 4'b1000;
        endcase
    end else out = 4'bzzzz;
    end
endmodule

midterm/encoder_decoder/tb_decoder2to4.v
`timescale 1ns / 1ps
module tb_decoder2to4;
reg [1:0] in;
reg en;
wire [3:0] out;

decoder2to4 uut(
    .in(in), .en(en), .out(out));

initial begin
    $dumpfile("decoder2to4.vcd");
    $dumpvars(0, tb_decoder2to4);

    $display("Time\tin\ten\tout");
    $monitor("\t%b\t%b\t%b", in, en, out);

    in = 2'b00;
    en = 0; #10;
    in = 2'b01; #10;
    in = 2'b10; #10;
    in = 2'b11; #10;

    en = 1; #10;
    in = 2'b00; #10;
    in = 2'b01; #10;
    in = 2'b10; #10;
    in = 2'b11; #10;

    $finish;
    end
endmodule

midterm/encoder_decoder/decoder2to4.vcd
$date
	Thu May 01 23:02:20 2025
$end
$version
	Icarus Verilog
$end
$timescale
	1ps
$end
$scope module tb_decoder2to4 $end
$var wire 4 ! out [3:0] $end
$var reg 1 " en $end
$var reg 2 # in [1:0] $end
$scope module uut $end
$var wire 1 " en $end
$var wire 2 $ in [1:0] $end
$var reg 4 % out [3:0] $end
$upscope $end
$upscope $end
$enddefinitions $end
$comment Show the parameter values. $end
$dumpall
$end
#0
$dumpvars
bz %
b0 $
b0 #
0"
bz !
$end
#10000
b1 #
b1 $
#20000
b10 #
b10 $
#30000
b11 #
b11 $
#40000
b1000 !
b1000 %
1"
#50000
b1 !
b1 %
b0 #
b0 $
#60000
b10 !
b10 %
b1 #
b1 $
#70000
b100 !
b100 %
b10 #
b10 $
#80000
b1000 !
b1000 %
b11 #
b11 $
