midterm/encoder_decoder/priority_encoder4to2.v
// Code your design here
module priority_encoder4to2(
  input wire [3:0] in,
  output reg valid,
  output reg [1:0] out);
  
  always@* begin
    if (in == 4'b0000) begin
      valid = 0;
      out = 2'bzz;
    end else begin
      valid = 1;
      casez(in)
        4'b0001: out = 2'b00;
        4'b001?: out = 2'b01;
		4'b01??: out = 2'b10;
        4'b1???: out = 2'b11;
      endcase
    end
  end
endmodule

midterm/encoder_decoder/tb_priority_encoder4to2.v
// Code your testbench here
// or browse Examples
`timescale 1ns / 1ps
module tb_priority_encoder4to2;
  reg [3:0] in;
  wire val;
  wire [1:0] out;
  
  priority_encoder4to2 uut(
    .in(in), .valid(valid), .out(out));
  
  initial begin
    $dumpfile("priority_encoder4to2.vcd");
    $dumpvars(0, tb_priority_encoder4to2);
    
	$display("Time\tin\tvalid\tout");
    $monitor("\t%b\t%b\t%b", in, valid, out);
    
    // Apply all 16 combinations
    in = 4'b0000; #10;
    in = 4'b0001; #10;
    in = 4'b0010; #10;
    in = 4'b0011; #10;
    in = 4'b0100; #10;
    in = 4'b0101; #10;
    in = 4'b0110; #10;
    in = 4'b0111; #10;
    in = 4'b1000; #10;
    in = 4'b1001; #10;
    in = 4'b1010; #10;
    in = 4'b1011; #10;
    in = 4'b1100; #10;
    in = 4'b1101; #10;
    in = 4'b1110; #10;
    in = 4'b1111; #10;

    $finish;
  end
endmodule

midterm/encoder_decoder/priority_encoder4to2.vcd
$date
	Thu May 01 22:30:31 2025
$end
$version
	Icarus Verilog
$end
$timescale
	1ps
$end
$scope module tb_priority_encoder4to2 $end
$var wire 1 ! valid $end
$var wire 2 " out [1:0] $end
$var reg 4 # in [3:0] $end
$scope module uut $end
$var wire 4 $ in [3:0] $end
$var reg 2 % out [1:0] $end
$var reg 1 ! valid $end
$upscope $end
$upscope $end
$enddefinitions $end
$comment Show the parameter values. $end
$dumpall
$end
#0
$dumpvars
bz %
b0 $
b0 #
bz "
0!
$end
#10000
b0 "
b0 %
1!
b1 #
b1 $
#20000
b1 "
b1 %
b10 #
b10 $
#30000
b11 #
b11 $
#40000
b10 "
b10 %
b100 #
b100 $
#50000
b101 #
b101 $
#60000
b110 #
b110 $
#70000
b111 #
b111 $
#80000
b11 "
b11 %
b1000 #
b1000 $
#90000
b1001 #
b1001 $
#100000
b1010 #
b1010 $
#110000
b1011 #
b1011 $
#120000
b1100 #
b1100 $
#130000
b1101 #
b1101 $
#140000
b1110 #
b1110 $
#150000
b1111 #
b1111 $
