midterm/encoder_decoder/priority_encoder8to3.v
module priority_encoder8to3(
    input wire [7:0] in,
    output reg valid,
    output reg [2:0] out );

always@ * begin
    if (in == 8'b00000000) begin
        valid = 0;
        out = 3'bzzz;
    end else begin
        valid = 1;
            casez(in)
                8'b00000001: out = 3'b000;
                8'b0000001?: out = 3'b001;
                8'b000001??: out = 3'b010;
                8'b00001???: out = 3'b011;
                8'b0001????: out = 3'b100;
                8'b001?????: out = 3'b101;
                8'b01??????: out = 3'b110;
                8'b1???????: out = 3'b111;
            endcase
        end
    end
endmodule

midterm/encoder_decoder/tb_priority_encoder8to3.v
`timescale 1ns / 1ps

module tb_priority_encoder8to3;

    reg [7:0] in;
    wire valid;
    wire [2:0] out;

    // Instantiate your DUT (Design Under Test)
    priority_encoder8to3 uut (
        .in(in),
        .valid(valid),
        .out(out)
    );

    initial begin
        $dumpfile("priority_encoder8to3.vcd");
        $dumpvars(0, tb_priority_encoder8to3);

    	$display("Time\tin\tvalid\tout");
        $monitor("\t%b\t%b\t%b", in, valid, out);

        // Apply test vectors
        in = 8'b00000000; #10; // No valid input
        in = 8'b00000001; #10; // LSB high → out = 000
        in = 8'b00000010; #10; // bit[1] high → out = 001
        in = 8'b00000100; #10; // bit[2] high → out = 010
        in = 8'b00001000; #10; // bit[3] high → out = 011
        in = 8'b00010000; #10; // bit[4] high → out = 100
        in = 8'b00100000; #10; // bit[5] high → out = 101
        in = 8'b01000000; #10; // bit[6] high → out = 110
        in = 8'b10000000; #10; // MSB high → out = 111

        // Multiple bits high → should pick highest priority (MSB)
        in = 8'b10101010; #10;

        $finish;
    end
endmodule

midterm/encoder_decoder/priority_encoder8to3.vcd
$date
	Thu May 01 22:42:17 2025
$end
$version
	Icarus Verilog
$end
$timescale
	1ps
$end
$scope module tb_priority_encoder8to3 $end
$var wire 1 ! valid $end
$var wire 3 " out [2:0] $end
$var reg 8 # in [7:0] $end
$scope module uut $end
$var wire 8 $ in [7:0] $end
$var reg 3 % out [2:0] $end
$var reg 1 ! valid $end
$upscope $end
$upscope $end
$enddefinitions $end
$comment Show the parameter values. $end
$dumpall
$end
#0
$dumpvars
bz %
b0 $
b0 #
bz "
0!
$end
#10000
b0 "
b0 %
1!
b1 #
b1 $
#20000
b1 "
b1 %
b10 #
b10 $
#30000
b10 "
b10 %
b100 #
b100 $
#40000
b11 "
b11 %
b1000 #
b1000 $
#50000
b100 "
b100 %
b10000 #
b10000 $
#60000
b101 "
b101 %
b100000 #
b100000 $
#70000
b110 "
b110 %
b1000000 #
b1000000 $
#80000
b111 "
b111 %
b10000000 #
b10000000 $
#90000
b10101010 #
b10101010 $
